wsterm/__init__.py
wsterm/__main__.py
wsterm/client.py
wsterm/gitignore_parser.py
wsterm/proto.py
wsterm/server.py
wsterm/shell.py
wsterm/utils.py
wsterm/workspace.py
wsterm/aiowatch/__init__.py
wsterm/aiowatch/inotify.py
wsterm/aiowatch/kevents.py
wsterm/aiowatch/win32.py
wsterm/bin/darwin/sz
wsterm/bin/linux/sz
wsterm/bin/win32/sz.exe
wsterm-0.7.1.dist-info/METADATA
wsterm-0.7.1.dist-info/WHEEL
wsterm-0.7.1.dist-info/entry_points.txt
wsterm-0.7.1.dist-info/top_level.txt
wsterm-0.7.1.dist-info/RECORD
