Metadata-Version: 2.1
Name: wsterm
Version: 0.7.1
Summary: Websocket remote debug terminal (auto sync workspace).
Home-page: https://github.com/wsterm/wsterm
Author: drunkdream
Author-email: drunkdream@qq.com
License: MIT
Classifier: Development Status :: 3 - Alpha
Classifier: License :: OSI Approved :: MIT License
Classifier: Programming Language :: Python
Classifier: Programming Language :: Python :: 3
Classifier: Programming Language :: Python :: 3.5
Classifier: Programming Language :: Python :: 3.6
Classifier: Programming Language :: Python :: 3.7
Classifier: Programming Language :: Python :: 3.8
Classifier: Programming Language :: Python :: 3.9
Classifier: Programming Language :: Python :: 3.10
Classifier: Programming Language :: Python :: 3.11
Classifier: Intended Audience :: Developers
Requires-Python: >=3.5
Requires-Dist: msgpack ==1.0.4
Requires-Dist: python-daemon
Requires-Dist: tornado ==6.1
Requires-Dist: pywin32 ==228 ; sys_platform == "win32" and python_version <= "3.7"
Requires-Dist: pywin32 ==306 ; sys_platform == "win32" and python_version > "3.7"
